even_odd_data_delay_ckt/even_odd_data_delay_ckt.srcs/sources_1/new/odd_data_delay.v
`timescale 1ns / 1ps
//////////////////////////////////////////////////////////////////////////////////
// Company: 
// Engineer: 
// 
// Create Date: 18.09.2025 19:13:54
// Design Name: 
// Module Name: odd_data_delay
// Project Name: 
// Target Devices: 
// Tool Versions: 
// Description: 
// 
// Dependencies: 
// 
// Revision:
// Revision 0.01 - File Created
// Additional Comments:
// 
//////////////////////////////////////////////////////////////////////////////////


module odd_data_delay #(
    parameter WIDTH = 8    // default width = 8 bits
)(
    input  wire              clk,     // clock
    input  wire              rst,     // synchronous active-high reset
    input  wire [WIDTH-1:0]  din,     // data input
    output wire  [WIDTH-1:0]  dout     // data output (delayed by 1 cycle)
);
    reg [WIDTH-1:0] dout_q;
    wire [WIDTH-1:0] mux;
    
    
    // ping pong enable logic
    reg ping_q;
    wire ping_w;
    always @(posedge clk) begin
        if (rst)
            ping_q <= {WIDTH{1'b0}};   
        else
            ping_q <= ping_w;          
    end
    
    assign ping_w = ~ ping_q;
    
    
    
    
  
    
    //mux logic
   
    assign mux = ping_q ? dout_q : din;
    
    // even data flop logic
    always @(posedge clk) begin
        if (rst)
            dout_q <= {WIDTH{1'b0}};   // reset clears flop
        else
            dout_q <= mux;             // capture input
    end

    
    //output logic 
    
    assign dout = ping_q ? din : dout_q;
    
    
endmodule

even_odd_data_delay_ckt/even_odd_data_delay_ckt.srcs/sim_1/new/tb_odd_data_delay.v
`timescale 1ns / 1ps
//////////////////////////////////////////////////////////////////////////////////
// Company: 
// Engineer: 
// 
// Create Date: 18.09.2025 19:28:24
// Design Name: 
// Module Name: tb_odd_data_delay
// Project Name: 
// Target Devices: 
// Tool Versions: 
// Description: 
// 
// Dependencies: 
// 
// Revision:
// Revision 0.01 - File Created
// Additional Comments:
// 
//////////////////////////////////////////////////////////////////////////////////


// tb_odd_data_delay.v
`timescale 1ns/1ps

module tb_odd_data_delay;

    // Parameters
    localparam WIDTH = 8;

    // Signals
    reg clk;
    reg rst;
    reg  [WIDTH-1:0] din;
    wire [WIDTH-1:0] dout;

    // DUT instantiation
    odd_data_delay #(.WIDTH(WIDTH)) DUT (
        .clk(clk),
        .rst(rst),
        .din(din),
        .dout(dout)
    );

    // Clock generation: 10 ns period
    initial clk = 0;
    always #5 clk = ~clk;

    // Stimulus
    initial begin
        // init
        rst = 1;
        din = 0;

        // waveform dump (for Vivado, you’ll see in GUI, this is useful in other sims)
        $dumpfile("tb_odd_data_delay.vcd");
        $dumpvars(0, tb_odd_data_delay);

        // hold reset for 2 cycles
        repeat (6) @(posedge clk);
        rst = 0;

        // Apply a sequence of data
        din = 8'h11;
        @(posedge clk);
        din = 8'h22;
        @(posedge clk);
        din = 8'h33;
        @(posedge clk);
        din = 8'h44;
        @(posedge clk);
        din = 8'h55;
        @(posedge clk);
        din = 8'h66;
        @(posedge clk);

        // hold value
        din = 8'h77;
        @(posedge clk);
        din = 8'h0;
        repeat (1) @(posedge clk);

        // end sim
        $display("Simulation finished at %0t", $time);
        $finish;
    end

endmodule

even_odd_data_delay_ckt/even_odd_data_delay_ckt.sim/sim_1/behav/xsim/tb_odd_data_delay.vcd
$date
   Thu Sep 18 19:38:44 2025
$end

$version
  2023.2
  $dumpfile ("tb_odd_data_delay.vcd") 
$end

$timescale
  1ps
$end

$scope module tb_odd_data_delay $end
$var reg 1 ! clk $end
$var reg 1 " rst $end
$var reg 8 # din [7:0] $end
$var wire 8 $ dout [7:0] $end
$scope module DUT $end
$var wire 1 % clk $end
$var wire 1 & rst $end
$var wire 8 ' din [7:0] $end
$var wire 8 $ dout [7:0] $end
$var reg 8 ( dout_q [7:0] $end
$var wire 8 ) mux [7:0] $end
$var reg 1 * ping_q $end
$var wire 1 + ping_w $end
$upscope $end
$upscope $end
$enddefinitions $end

#0
$dumpvars
0!
1"
b0 #
bx $
0%
1&
b0 '
bx (
bx )
x*
x+
$end

#5000
1!
b0 $
1%
b0 (
b0 )
0*
1+

#10000
0!
0%

#15000
1!
1%

#20000
0!
0%

#25000
1!
1%

#30000
0!
0%

#35000
1!
1%

#40000
0!
0%

#45000
1!
1%

#50000
0!
0%

#55000
1!
0"
b10001 #
b10001 $
1%
0&
b10001 '
b0 )
1*
0+

#60000
0!
0%

#65000
1!
b100010 #
b0 $
1%
b100010 '
b100010 )
0*
1+

#70000
0!
0%

#75000
1!
b110011 #
b110011 $
1%
b110011 '
b100010 (
b100010 )
1*
0+

#80000
0!
0%

#85000
1!
b1000100 #
b100010 $
1%
b1000100 '
b1000100 )
0*
1+

#90000
0!
0%

#95000
1!
b1010101 #
b1010101 $
1%
b1010101 '
b1000100 (
b1000100 )
1*
0+

#100000
0!
0%

#105000
1!
b1100110 #
b1000100 $
1%
b1100110 '
b1100110 )
0*
1+

#110000
0!
0%

#115000
1!
b1110111 #
b1110111 $
1%
b1110111 '
b1100110 (
b1100110 )
1*
0+

#120000
0!
0%

#125000
1!
b0 #
b1100110 $
1%
b0 '
b0 )
0*
1+

